ttyg/__init__.py
ttyg/agents/__init__.py
ttyg/agents/run_agent.py
ttyg/agents/run_agent_for_evaluation.py
ttyg/graphdb/__init__.py
ttyg/graphdb/graphdb.py
ttyg/tools/__init__.py
ttyg/tools/base_artifact.py
ttyg/tools/graphdb_tools/__init__.py
ttyg/tools/graphdb_tools/autocomplete_search_tool.py
ttyg/tools/graphdb_tools/base.py
ttyg/tools/graphdb_tools/fts_tool.py
ttyg/tools/graphdb_tools/iri_discovery_tool.py
ttyg/tools/graphdb_tools/ontology_schema_and_vocabulary_tool.py
ttyg/tools/graphdb_tools/retrieval_query_tool.py
ttyg/tools/graphdb_tools/similarity_search_query_tool.py
ttyg/tools/graphdb_tools/sparql_query_artifact.py
ttyg/tools/graphdb_tools/sparql_query_tool.py
ttyg/tools/now_tool.py
ttyg/utils/__init__.py
ttyg/utils/set_env.py
ttyg/utils/timeit.py
ttyg-3.1.0.dist-info/LICENSE
ttyg-3.1.0.dist-info/METADATA
ttyg-3.1.0.dist-info/WHEEL
ttyg-3.1.0.dist-info/RECORD
