Metadata-Version: 2.3
Name: ttyg
Version: 3.1.0
Summary: Natural language querying for GraphDB using LangGraph agents
License: Apache-2.0
Requires-Python: >=3.12,<3.14
Classifier: License :: OSI Approved :: Apache Software License
Classifier: Programming Language :: Python :: 3
Classifier: Programming Language :: Python :: 3.12
Classifier: Programming Language :: Python :: 3.13
Requires-Dist: langchain (==1.2.3)
Requires-Dist: langgraph (==1.0.5)
Requires-Dist: sparqlwrapper (==2.0.0)
Project-URL: Repository, https://github.com/Ontotext-AD/ttyg-langgraph
